email_dump.py
email_dump-0.1.0.dist-info/LICENSE
email_dump-0.1.0.dist-info/METADATA
email_dump-0.1.0.dist-info/WHEEL
email_dump-0.1.0.dist-info/entry_points.txt
email_dump-0.1.0.dist-info/top_level.txt
email_dump-0.1.0.dist-info/RECORD
