Metadata-Version: 2.1
Name: email-dump
Version: 0.1.0
Summary: Dump all the mails sent by a specific user
Home-page: https://github.com/Adwaith-Rajesh/email-dump
Author: Adwaith Rajesh
Author-email: adwaithrajesh3180@gmail.com
License: MIT
Classifier: License :: OSI Approved :: MIT License
Classifier: Programming Language :: Python :: 3
Classifier: Programming Language :: Python :: 3 :: Only
Classifier: Programming Language :: Python :: 3.10
Requires-Python: >=3.10.0
License-File: LICENSE
Requires-Dist: imap-tools (>=1.0.0)
